.DS_Store
wcwidth/__init__.py
wcwidth/emoji_zwj_sequences.py
wcwidth/py.typed
wcwidth/table_vs16.py
wcwidth/table_wide.py
wcwidth/table_zero.py
wcwidth/unicode_versions.py
wcwidth/unicode_versions.pyi
wcwidth/wcwidth.py
wcwidth/wcwidth.pyi
wcwidth-0.2.11.dist-info/LICENSE
wcwidth-0.2.11.dist-info/METADATA
wcwidth-0.2.11.dist-info/WHEEL
wcwidth-0.2.11.dist-info/top_level.txt
wcwidth-0.2.11.dist-info/zip-safe
wcwidth-0.2.11.dist-info/RECORD
